defn_cdktf_provider_buildkite/__init__.py
defn_cdktf_provider_buildkite/main.py
defn_cdktf_provider_buildkite/_jsii/__init__.py
defn_cdktf_provider_buildkite/_jsii/buildkite_buildkite@0.0.0.jsii.tgz
defn_cdktf_provider_buildkite/_jsii/main.py
defn_cdktf_provider_buildkite-0.4.1.dist-info/METADATA
defn_cdktf_provider_buildkite-0.4.1.dist-info/WHEEL
defn_cdktf_provider_buildkite-0.4.1.dist-info/namespace_packages.txt
defn_cdktf_provider_buildkite-0.4.1.dist-info/top_level.txt
defn_cdktf_provider_buildkite-0.4.1.dist-info/RECORD
